splade4elastic/__init__.py
splade4elastic/elastic_splade.py
splade4elastic-0.0.23.dist-info/METADATA
splade4elastic-0.0.23.dist-info/WHEEL
splade4elastic-0.0.23.dist-info/top_level.txt
splade4elastic-0.0.23.dist-info/RECORD
