Metadata-Version: 2.1
Name: splade4elastic
Version: 0.0.23
Home-page: https://github.com/argmaxml/splade4elastic
Author: ArgmaxML
Author-email: splade@argmaxml.com
Requires-Dist: numpy >=1.21.2
Requires-Dist: transformers >=4.0.0
Provides-Extra: elasticsearch
Requires-Dist: elasticsearch >=8.5.0 ; extra == 'elasticsearch'
Provides-Extra: faiss
Requires-Dist: faiss-cpu >=1.7.1 ; extra == 'faiss'
